glimlach/__init__.py
glimlach/__main__.py
glimlach/cli.py
glimlach-0.4.7.dist-info/METADATA
glimlach-0.4.7.dist-info/WHEEL
glimlach-0.4.7.dist-info/entry_points.txt
glimlach-0.4.7.dist-info/top_level.txt
glimlach-0.4.7.dist-info/RECORD
