Metadata-Version: 2.1
Name: glimlach
Version: 0.4.7
Summary: Glimlach is a project that allows you to easily run Docker images based on a configuration file.
Home-page: https://github.com/firstnuel/Glimlach
Author: 'Emmanuel Ikwunna', 'Arttu Juntunen', 'Piyumi Weebadu Arachchige'
Requires-Dist: docker (>=4.4.4)
